setup.py
azurecs/__init__.py
azurecs/exceptions.py
azurecs.egg-info/PKG-INFO
azurecs.egg-info/SOURCES.txt
azurecs.egg-info/dependency_links.txt
azurecs.egg-info/top_level.txt
azurecs/knowledge/__init__.py
azurecs/language/__init__.py
azurecs/language/spellcheck.py
azurecs/language/translate.py
azurecs/speech/__init__.py
azurecs/vision/__init__.py