Metadata-Version: 1.0
Name: azurecs
Version: 0.1
Summary: Python wrapper for the client-side APIs of Microsoft Azure Cognitive Services
Home-page: https://github.com/flyinactor91/AzureCS
Author: Michael duPont
Author-email: michael@mdupont.com
License: UNKNOWN
Platform: UNKNOWN
